py_wsl_scraper-0.1.1.dist-info/licenses/LICENSE
pywsl/__init__.py
pywsl/display.py
pywsl/fixtures.py
pywsl/league.py
pywsl/scorers.py
pywsl/squads.py
pywsl/venue.py
py_wsl_scraper-0.1.1.dist-info/METADATA
py_wsl_scraper-0.1.1.dist-info/WHEEL
py_wsl_scraper-0.1.1.dist-info/top_level.txt
py_wsl_scraper-0.1.1.dist-info/RECORD
