Metadata-Version: 2.4
Name: py_wsl_scraper
Version: 0.1.1
Summary: A Python package for scraping Women's Super League (WSL) football data
Author-email: Ellie <ellbindi@outlook.com>
License: MIT
Keywords: football,wsl,data,scraping,sports
Classifier: Programming Language :: Python :: 3
Classifier: License :: OSI Approved :: MIT License
Classifier: Operating System :: OS Independent
Classifier: Intended Audience :: Developers
Classifier: Topic :: Software Development :: Libraries :: Python Modules
Requires-Python: >=3.9
License-File: LICENSE
Requires-Dist: pandas
Requires-Dist: requests
Requires-Dist: beautifulsoup4
Requires-Dist: selenium
Requires-Dist: webdriver-manager
Dynamic: license-file
